{"cameraMode":{"drawMode":0,"name":"Shaded","section":"Shading Mode"},"sceneLighting":true,"audioPlay":false,"sceneViewState":{"showFog":true,"showMaterialUpdate":false,"showSkybox":true,"showFlares":true,"showImageEffects":true,"showParticleSystems":true},"in2DMode":false,"pivot":{"x":173.00473022460938,"y":-1.2931544780731202,"z":-907.1426391601563},"rotation":{"x":-0.2678637206554413,"y":0.5992642641067505,"z":-0.22270241379737855,"w":-0.7207877039909363},"size":80.35069274902344,"orthographic":false}